vault_crio/__init__.py
vault_crio/vault.py
vault_crio-1.0.0.dist-info/METADATA
vault_crio-1.0.0.dist-info/WHEEL
vault_crio-1.0.0.dist-info/top_level.txt
vault_crio-1.0.0.dist-info/RECORD
