Metadata-Version: 2.1
Name: vault-crio
Version: 1.0.0
Summary: Vault library
Author: Ravi Raj
Classifier: Intended Audience :: Developers
Classifier: License :: OSI Approved :: MIT License
Classifier: Programming Language :: Python
Classifier: Programming Language :: Python :: 3
Classifier: Programming Language :: Python :: 3.6
Classifier: Programming Language :: Python :: 3.7
Classifier: Programming Language :: Python :: 3.8
Classifier: Programming Language :: Python :: 3.9
Classifier: Operating System :: OS Independent
Requires-Dist: botocore
Requires-Dist: boto3
Requires-Dist: requests
